code8/__init__.py
code8/cli.py
code8/config_ui.py
code8/test_generator.py
code8/static/styles.css
code8/templates/index.html
code8-0.1.6.dist-info/LICENSE
code8-0.1.6.dist-info/METADATA
code8-0.1.6.dist-info/WHEEL
code8-0.1.6.dist-info/entry_points.txt
code8-0.1.6.dist-info/top_level.txt
code8-0.1.6.dist-info/RECORD
