Metadata-Version: 2.1
Name: code8
Version: 0.1.6
Summary: a dashboard to use LLMs to directly on your code files, save and load custom profiles with custom prompts and more.
Home-page: https://github.com/naserjamal/code8
Author: Naser Jamal
Author-email: naser.dll@hotmail.com
License: UNKNOWN
Platform: UNKNOWN
Classifier: Programming Language :: Python :: 3
Classifier: License :: OSI Approved :: MIT License
Classifier: Operating System :: OS Independent
License-File: LICENSE
Requires-Dist: Flask
Requires-Dist: openai
Requires-Dist: anthropic
Requires-Dist: argparse
